[
  {
    "asset": "W",
    "exchange": "Drift",
    "strategy": "IBB",
    "direction": "SHORT",
    "leverage": 5,
    "entryPrice": 0.020029,
    "currentPrice": 0.020029,
    "stopLoss": 0.020292400000000002,
    "takeProfit": 0.0196778,
    "positionSize": 375,
    "unrealizedPnl": 0,
    "unrealizedPnlPct": 0,
    "entryTime": "2026-02-21T00:01:56.451Z"
  },
  {
    "asset": "XRP",
    "exchange": "Drift",
    "strategy": "IBB",
    "direction": "SHORT",
    "leverage": 5,
    "entryPrice": 1.4359600000000001,
    "currentPrice": 1.4359600000000001,
    "stopLoss": 1.4448274,
    "takeProfit": 1.4241368,
    "positionSize": 375,
    "unrealizedPnl": 0,
    "unrealizedPnlPct": 0,
    "entryTime": "2026-02-21T21:01:59.091Z"
  }
]