{
  "lastUpdate": "2026-02-20T16:10:13.554Z",
  "version": "MegaMax v1.4",
  "status": "LIVE",
  "dataSource": "drift-direct",
  "account": {
    "exchange": "drift",
    "equity": 4560.7,
    "freeCollateral": 4426.69,
    "leverage": 0.31,
    "startingEquity": 1868.46,
    "wallet": "3gPExFYHC8fqkwwrb6De8n9fwYdbJPBG3XYLstKNNkt7"
  },
  "openPositions": [
    {
      "exchange": "drift",
      "symbol": "SUI",
      "direction": "SHORT",
      "strategy": "V5.0",
      "entry": 0.9687,
      "current": 0.9756,
      "size": 1414.6,
      "sizeUnits": 1450,
      "pnl": 0,
      "pnlPercent": 0
    }
  ],
  "stats": {
    "totalTrades": 136,
    "wins": 8,
    "losses": 2,
    "winRate": 80,
    "totalPnl": 386.25,
    "avgPnl": 38.625
  },
  "recentTrades": [
    {
      "id": "WIF-1771598053490",
      "symbol": "WIF",
      "strategy": "IBB",
      "direction": "SHORT",
      "entry": 0.214647,
      "exit": 0.21035406,
      "pnl": 50,
      "pnlPercent": 10,
      "exitTime": "2026-02-20T14:34:13.490Z",
      "status": "CLOSED"
    },
    {
      "id": "TIA-1771597693803",
      "symbol": "TIA",
      "strategy": "VWAP-RSI",
      "direction": "SHORT",
      "entry": 0.319019,
      "exit": 0.31263862,
      "pnl": 50,
      "pnlPercent": 10,
      "exitTime": "2026-02-20T14:28:13.803Z",
      "status": "CLOSED"
    },
    {
      "id": "PEPE-1771597693803",
      "symbol": "PEPE",
      "strategy": "VWAP-RSI",
      "direction": "SHORT",
      "entry": 4.1116,
      "exit": 4.029368,
      "pnl": 50,
      "pnlPercent": 10,
      "exitTime": "2026-02-20T14:28:13.803Z",
      "status": "CLOSED"
    },
    {
      "id": "PEPE-1771596335835",
      "symbol": "PEPE",
      "strategy": "VWAP-RSI",
      "direction": "SHORT",
      "entry": 4.1116,
      "exit": 4.1317,
      "pnl": -13.75,
      "pnlPercent": -2.44,
      "entryTime": "2026-02-20T14:05:35.837Z",
      "exitTime": "2026-02-20T14:28:01.891Z",
      "status": "CLOSED"
    },
    {
      "id": "SOL-1771588212932",
      "symbol": "SOL",
      "strategy": "V5.0",
      "direction": "SHORT",
      "entry": 84.520547,
      "exit": 82.83013605999999,
      "pnl": 50,
      "pnlPercent": 10,
      "exitTime": "2026-02-20T11:50:12.932Z",
      "status": "CLOSED"
    },
    {
      "id": "PYTH-1771587972880",
      "symbol": "PYTH",
      "strategy": "VWAP-RSI",
      "direction": "LONG",
      "entry": 0.053523,
      "exit": 0.05459346,
      "pnl": 50,
      "pnlPercent": 10,
      "exitTime": "2026-02-20T11:46:12.880Z",
      "status": "CLOSED"
    },
    {
      "id": "SUI-1771587972880",
      "symbol": "SUI",
      "strategy": "V5.0",
      "direction": "SHORT",
      "entry": 0.954668,
      "exit": 0.9355746399999999,
      "pnl": 50,
      "pnlPercent": 10,
      "exitTime": "2026-02-20T11:46:12.880Z",
      "status": "CLOSED"
    },
    {
      "id": "JTO-1771583692644",
      "symbol": "JTO",
      "strategy": "VWAP-RSI",
      "direction": "LONG",
      "entry": 0.312524,
      "exit": 0.31877448,
      "pnl": 50,
      "pnlPercent": 10,
      "exitTime": "2026-02-20T10:34:52.644Z",
      "status": "CLOSED"
    },
    {
      "id": "JTO-1771581336731",
      "symbol": "JTO",
      "strategy": "VWAP-RSI",
      "direction": "LONG",
      "entry": 0.312524,
      "exit": 0.312524,
      "pnl": 0,
      "pnlPercent": 0,
      "entryTime": "2026-02-20T09:55:36.733Z",
      "exitTime": "2026-02-20T10:13:24.491Z",
      "status": "CLOSED"
    },
    {
      "id": "WIF-1771565774137",
      "symbol": "WIF",
      "strategy": "IBB",
      "direction": "SHORT",
      "entry": 0.216341,
      "exit": 0.21201418,
      "pnl": 50,
      "pnlPercent": 10,
      "exitTime": "2026-02-20T05:36:14.137Z",
      "status": "CLOSED"
    }
  ],
  "strategies": {
    "V5.0": {
      "assets": [
        "SUI",
        "SOL",
        "DOGE",
        "PEPE",
        "XRP"
      ],
      "exchange": "Drift",
      "type": "Mean Reversion",
      "params": {
        "sl": "1.0x ATR",
        "tp": "2.0x ATR",
        "trendFilter": "20 EMA"
      }
    },
    "IBB": {
      "assets": [
        "WIF",
        "DOT",
        "W",
        "XRP"
      ],
      "exchange": "Drift",
      "type": "Inside Bar Breakout",
      "params": {
        "sl": "1.5x ATR",
        "tp": "2.0x ATR",
        "trendFilter": "20 EMA"
      }
    },
    "LC": {
      "assets": [
        "OP",
        "ARB",
        "RNDR",
        "ATOM",
        "DOT",
        "NEAR"
      ],
      "exchange": "Kraken",
      "type": "RSI(2) Daily",
      "params": {
        "sl": "2.0x ATR",
        "tp": "4.0x ATR"
      }
    },
    "MOMENTUM": {
      "assets": [
        "WIF",
        "PEPE",
        "INJ",
        "RNDR"
      ],
      "exchange": "Drift",
      "type": "Daily Breakouts",
      "params": {
        "sl": "1.5x ATR",
        "tp": "3.0x ATR",
        "trendFilter": "20 EMA"
      }
    },
    "VWAP-RSI": {
      "assets": [
        "PEPE",
        "TIA",
        "JTO",
        "DOT",
        "RNDR",
        "PYTH",
        "LINK",
        "ATOM",
        "INJ"
      ],
      "exchange": "Drift",
      "type": "5min Scalper",
      "params": {
        "sl": "1.0x ATR",
        "tp": "2.0x ATR",
        "rsi": 3
      }
    }
  }
}